cloudsmith_api/__init__.py
cloudsmith_api/api_client.py
cloudsmith_api/configuration.py
cloudsmith_api/rest.py
cloudsmith_api/api/__init__.py
cloudsmith_api/api/audit_log_api.py
cloudsmith_api/api/badges_api.py
cloudsmith_api/api/broadcasts_api.py
cloudsmith_api/api/distros_api.py
cloudsmith_api/api/entitlements_api.py
cloudsmith_api/api/files_api.py
cloudsmith_api/api/formats_api.py
cloudsmith_api/api/metrics_api.py
cloudsmith_api/api/namespaces_api.py
cloudsmith_api/api/orgs_api.py
cloudsmith_api/api/packages_api.py
cloudsmith_api/api/quota_api.py
cloudsmith_api/api/rates_api.py
cloudsmith_api/api/repos_api.py
cloudsmith_api/api/status_api.py
cloudsmith_api/api/storage_regions_api.py
cloudsmith_api/api/user_api.py
cloudsmith_api/api/users_api.py
cloudsmith_api/api/vulnerabilities_api.py
cloudsmith_api/api/webhooks_api.py
cloudsmith_api/models/__init__.py
cloudsmith_api/models/allocated_limit.py
cloudsmith_api/models/allocated_limit_raw.py
cloudsmith_api/models/alpine_package_upload.py
cloudsmith_api/models/alpine_package_upload_request.py
cloudsmith_api/models/architecture.py
cloudsmith_api/models/broadcast_token.py
cloudsmith_api/models/broadcast_token_input.py
cloudsmith_api/models/cargo_package_upload.py
cloudsmith_api/models/cargo_package_upload_request.py
cloudsmith_api/models/cargo_upstream.py
cloudsmith_api/models/cargo_upstream_request.py
cloudsmith_api/models/cargo_upstream_request_patch.py
cloudsmith_api/models/cocoapods_package_upload.py
cloudsmith_api/models/cocoapods_package_upload_request.py
cloudsmith_api/models/common_bandwidth_metrics.py
cloudsmith_api/models/common_bandwidth_metrics_value.py
cloudsmith_api/models/common_downloads_metrics.py
cloudsmith_api/models/common_downloads_metrics_value.py
cloudsmith_api/models/common_metrics.py
cloudsmith_api/models/composer_package_upload.py
cloudsmith_api/models/composer_package_upload_request.py
cloudsmith_api/models/composer_upstream.py
cloudsmith_api/models/composer_upstream_request.py
cloudsmith_api-2.0.24.dist-info/METADATA
cloudsmith_api-2.0.24.dist-info/WHEEL
cloudsmith_api-2.0.24.dist-info/top_level.txt
cloudsmith_api-2.0.24.dist-info/RECORD
