Metadata-Version: 2.1
Name: cloudsmith-api
Version: 2.0.24
Summary: Cloudsmith API (v1)
Home-page: https://api.cloudsmith.io/?format&#x3D;openapi
Author-email: support@cloudsmith.io
Keywords: Swagger,Cloudsmith API (v1)
Requires-Dist: certifi (>=2017.4.17)
Requires-Dist: python-dateutil (>=2.1)
Requires-Dist: six (>=1.10)
Requires-Dist: urllib3 (>=1.23)
